mkdocs_placeholder_plugin/__init__.py
mkdocs_placeholder_plugin/assets/__init__.py
mkdocs_placeholder_plugin/assets/placeholder-data.js
mkdocs_placeholder_plugin/assets/placeholder.min.js
mkdocs_placeholder_plugin/assets/placeholder.min.js.map
mkdocs_placeholder_plugin/generic/__init__.py
mkdocs_placeholder_plugin/generic/generic_style.py
mkdocs_placeholder_plugin/generic/html_tag_handler.py
mkdocs_placeholder_plugin/generic/html_tag_parser.py
mkdocs_placeholder_plugin/generic/json_generator.py
mkdocs_placeholder_plugin/generic/page_processor.py
mkdocs_placeholder_plugin/generic/config/__init__.py
mkdocs_placeholder_plugin/generic/config/configuration.py
mkdocs_placeholder_plugin/generic/config/parser_utils.py
mkdocs_placeholder_plugin/generic/config/placeholder.py
mkdocs_placeholder_plugin/generic/config/validator.py
mkdocs_placeholder_plugin/generic/static/__init__.py
mkdocs_placeholder_plugin/generic/static/input_elements.py
mkdocs_placeholder_plugin/generic/static/placeholder_replacer.py
mkdocs_placeholder_plugin/generic/static/table_generator.py
mkdocs_placeholder_plugin/generic/static/table_replacer.py
mkdocs_placeholder_plugin/generic/validators/__init__.py
mkdocs_placeholder_plugin/generic/validators/files.py
mkdocs_placeholder_plugin/generic/validators/internet.py
mkdocs_placeholder_plugin/generic/validators/ip_address.py
mkdocs_placeholder_plugin/generic/validators/network.py
mkdocs_placeholder_plugin/mkdocs/__init__.py
mkdocs_placeholder_plugin/mkdocs/plugin.py
mkdocs_placeholder_plugin/mkdocs/plugin_config.py
mkdocs_placeholder_plugin/mkdocs/style.py
mkdocs_placeholder_plugin/mkdocs/utils.py
mkdocs_placeholder_plugin-0.5.1.dist-info/LICENSE
mkdocs_placeholder_plugin-0.5.1.dist-info/METADATA
mkdocs_placeholder_plugin-0.5.1.dist-info/WHEEL
mkdocs_placeholder_plugin-0.5.1.dist-info/entry_points.txt
mkdocs_placeholder_plugin-0.5.1.dist-info/top_level.txt
mkdocs_placeholder_plugin-0.5.1.dist-info/RECORD
