Metadata-Version: 2.2
Name: mkdocs-placeholder-plugin
Version: 0.5.1
Summary: Add dynamic placeholders to your mkdocs page
Home-page: https://github.com/six-two/mkdocs-placeholder-plugin
Author: six-two
Author-email: pip@six-two.dev
License: MIT License
Classifier: License :: OSI Approved :: MIT License
Classifier: Operating System :: POSIX :: Linux
Classifier: Programming Language :: Python :: 3
Classifier: Programming Language :: Python :: 3.9
Classifier: Programming Language :: Python :: 3.10
Classifier: Programming Language :: Python :: 3.11
Requires-Python: >=3.9
License-File: LICENSE
Requires-Dist: mkdocs>=1.4.0
